sucket/__init__.py
sucket/bucket.py
sucket/types.py
sucket/utils.py
sucket-0.3.4.dist-info/entry_points.txt
sucket-0.3.4.dist-info/WHEEL
sucket-0.3.4.dist-info/METADATA
sucket-0.3.4.dist-info/RECORD
